ml_python_package/__init__.py
ml_python_package/train/__init__.py
ml_python_package/train/train_model.py
ml_python_package-0.1.5.dist-info/LICENSE
ml_python_package-0.1.5.dist-info/METADATA
ml_python_package-0.1.5.dist-info/WHEEL
ml_python_package-0.1.5.dist-info/top_level.txt
ml_python_package-0.1.5.dist-info/RECORD
