Metadata-Version: 2.1
Name: ml-python-package
Version: 0.1.5
Summary: Training stuff
Author: Mikhail Maryufich
License: MIT
License-File: LICENSE
Requires-Dist: scikit-learn (==0.24.1)
Requires-Dist: pandas (==1.1.5)
